fastgraphFPMS.cp313-win_amd64.pyd
examples/basic_usage.py
fastgraphfpms-1.0.5.dist-info/licenses/LICENSE
python/fastgraphFPMS_module.cpp
src/graph.cpp
src/graph.h
tests/input_1.txt
tests/input_10.txt
tests/input_11.txt
tests/input_2.txt
tests/input_3.txt
tests/input_4.txt
tests/input_5.txt
tests/input_6.txt
tests/input_7.txt
tests/input_8.txt
tests/input_9.txt
tests/output_1.txt
tests/output_2.txt
tests/output_3.txt
tests/output_4.txt
tests/output_5.txt
tests/test_basic.py
tests/test_performance.py
fastgraphfpms-1.0.5.dist-info/METADATA
fastgraphfpms-1.0.5.dist-info/WHEEL
fastgraphfpms-1.0.5.dist-info/top_level.txt
fastgraphfpms-1.0.5.dist-info/RECORD
