Metadata-Version: 2.4
Name: fastgraphFPMS
Version: 1.0.5
Summary: Fast Graph Algorithms Library implemented in C++
Author: Flavio D.
Author-email: "Flavio D." <drogoflavio16@gmail.com>
Project-URL: Homepage, https://github.com/16Flavio/fastgraphFPMS
Project-URL: Documentation, https://github.com/16Flavio/fastgraphFPMS#readme
Project-URL: Repository, https://github.com/16Flavio/fastgraphFPMS
Classifier: Development Status :: 3 - Alpha
Classifier: Intended Audience :: Developers
Classifier: License :: OSI Approved :: MIT License
Classifier: Programming Language :: Python :: 3
Classifier: Programming Language :: C++
Requires-Python: >=3.7
License-File: LICENSE
Requires-Dist: pybind11>=2.6.0
Dynamic: author
Dynamic: license-file
Dynamic: requires-python
